MANIFEST.in
README.rst
pyproject.toml
setup.cfg
setup.py
src/iot_grpc/__init__.py
src/iot_grpc/alerts.proto
src/iot_grpc/alerts_pb2.py
src/iot_grpc/alerts_pb2.pyi
src/iot_grpc/alerts_pb2_grpc.py
src/iot_grpc/measurements.proto
src/iot_grpc/measurements_pb2.py
src/iot_grpc/measurements_pb2.pyi
src/iot_grpc/measurements_pb2_grpc.py
src/ngits_iot_grpc.egg-info/PKG-INFO
src/ngits_iot_grpc.egg-info/SOURCES.txt
src/ngits_iot_grpc.egg-info/dependency_links.txt
src/ngits_iot_grpc.egg-info/requires.txt
src/ngits_iot_grpc.egg-info/top_level.txt