Metadata-Version: 2.1
Name: ngits-iot-grpc
Version: 0.0.8
Summary: Base gRPC protos for NGITS IoT
Home-page: https://ngits.dev
Author: NGITs
License: BSD-3-Clause
Classifier: Intended Audience :: Developers
Classifier: Operating System :: OS Independent
Classifier: Programming Language :: Python :: 3.11
Requires-Python: >=3.11
